web_app/__init__.py
web_app/app.py
web_app/templates/index.html
website_monitor/__init__.py
website_monitor/config.json
website_monitor/db_utils.py
website_monitor/website_monitor.py
website_monitor/wm_exceptions.py
website_monitor/logs/logfile
website_monitor-0.1.2.dist-info/DESCRIPTION.rst
website_monitor-0.1.2.dist-info/METADATA
website_monitor-0.1.2.dist-info/RECORD
website_monitor-0.1.2.dist-info/WHEEL
website_monitor-0.1.2.dist-info/entry_points.txt
website_monitor-0.1.2.dist-info/metadata.json
website_monitor-0.1.2.dist-info/top_level.txt
