Metadata-Version: 2.0
Name: website-monitor
Version: 0.1.2
Summary: Website Monitor is a program used for monitoring web sites and reporting their availability.
Home-page: https://github.com/an0o0nym/website_monitor
Author: Damian P.
Author-email: an0o0nyme@gmail.com
License: MIT license
Keywords: website_monitor
Platform: UNKNOWN
Classifier: Development Status :: 2 - Pre-Alpha
Classifier: Intended Audience :: Developers
Classifier: License :: OSI Approved :: MIT License
Classifier: Natural Language :: English
Classifier: Programming Language :: Python :: 3
Classifier: Programming Language :: Python :: 3.4
Classifier: Programming Language :: Python :: 3.5
Classifier: Programming Language :: Python :: 3.6
Requires-Dist: Flask (==0.12.2)
Requires-Dist: requests (==2.18.4)
